LICENSE
README.rst
pyproject.toml
sctp.py
setup.py
C/sctp.c
C/sctp_error.h
C/sctp_event.c
C/sctp_info.c
C/sctp_info_capi.h
_sctp/__init__.py
py3_sctp.egg-info/PKG-INFO
py3_sctp.egg-info/SOURCES.txt
py3_sctp.egg-info/dependency_links.txt
py3_sctp.egg-info/top_level.txt